pysnippets/__init__.py
pysnippets/compat.py
pysnippets/dictsnippets.py
pysnippets/listsnippets.py
pysnippets/strsnippets.py
pysnippets-1.1.4.dist-info/METADATA
pysnippets-1.1.4.dist-info/WHEEL
pysnippets-1.1.4.dist-info/top_level.txt
pysnippets-1.1.4.dist-info/RECORD
